openTSNE/__init__.py
openTSNE/_tsne.cp311-win_amd64.pyd
openTSNE/affinity.py
openTSNE/callbacks.py
openTSNE/initialization.py
openTSNE/kl_divergence.cp311-win_amd64.pyd
openTSNE/metrics.py
openTSNE/nearest_neighbors.py
openTSNE/quad_tree.cp311-win_amd64.pyd
openTSNE/sklearn.py
openTSNE/tsne.py
openTSNE/utils.py
openTSNE/version.py
openTSNE/_matrix_mul/__init__.py
openTSNE/_matrix_mul/matrix_mul.cp311-win_amd64.pyd
openTSNE/dependencies/__init__.py
openTSNE/dependencies/annoy/__init__.py
openTSNE/dependencies/annoy/annoylib.cp311-win_amd64.pyd
openTSNE-1.0.2.dist-info/LICENSE
openTSNE-1.0.2.dist-info/METADATA
openTSNE-1.0.2.dist-info/WHEEL
openTSNE-1.0.2.dist-info/top_level.txt
openTSNE-1.0.2.dist-info/RECORD
