Metadata-Version: 2.1
Name: openTSNE
Version: 1.0.2
Summary: Extensible, parallel implementations of t-SNE
Home-page: https://github.com/pavlin-policar/openTSNE
Author: Pavlin Poličar
Author-email: pavlin.g.p@gmail.com
License: BSD-3-Clause
Project-URL: Documentation, https://opentsne.readthedocs.io/
Project-URL: Source, https://github.com/pavlin-policar/openTSNE
Project-URL: Issue Tracker, https://github.com/pavlin-policar/openTSNE/issues
Classifier: Development Status :: 5 - Production/Stable
Classifier: Intended Audience :: Science/Research
Classifier: Intended Audience :: Developers
Classifier: Topic :: Software Development
Classifier: Topic :: Scientific/Engineering
Classifier: Operating System :: Microsoft :: Windows
Classifier: Operating System :: POSIX
Classifier: Operating System :: Unix
Classifier: Operating System :: MacOS
Classifier: License :: OSI Approved
Classifier: Programming Language :: Python :: 3
Classifier: Topic :: Scientific/Engineering :: Artificial Intelligence
Classifier: Topic :: Scientific/Engineering :: Visualization
Classifier: Topic :: Software Development :: Libraries :: Python Modules
Requires-Python: >=3.9
License-File: LICENSE
Requires-Dist: numpy>=1.16.6
Requires-Dist: scikit-learn>=0.20
Requires-Dist: scipy
Provides-Extra: hnsw
Requires-Dist: hnswlib~=0.4.0; extra == "hnsw"
Provides-Extra: pynndescent
Requires-Dist: pynndescent~=0.5.0; extra == "pynndescent"
